cafga/__init__.py
cafga/cafga(backup).py
cafga/cafga.py
cafga/config.py
cafga/containers.py
cafga/util.py
cafga/demo/src/demo/__init__.py
cafga/explainers/__init__.py
cafga/explainers/cafga_captum/__init__.py
cafga/explainers/cafga_captum/_utils/__init__.py
cafga/explainers/cafga_captum/_utils/common.py
cafga/explainers/cafga_captum/_utils/exceptions.py
cafga/explainers/cafga_captum/_utils/progress.py
cafga/explainers/cafga_captum/_utils/transformers_typing.py
cafga/explainers/cafga_captum/_utils/typing.py
cafga/explainers/cafga_captum/_utils/models/__init__.py
cafga/explainers/cafga_captum/_utils/models/model.py
cafga/explainers/cafga_captum/_utils/models/linear_model/__init__.py
cafga/explainers/cafga_captum/_utils/models/linear_model/model.py
cafga/explainers/cafga_captum/_utils/models/linear_model/train.py
cafga/explainers/cafga_captum/attr/__init__.py
cafga/explainers/cafga_captum/attr/_core/__init__.py
cafga/explainers/cafga_captum/attr/_core/dataloader_attr.py
cafga/explainers/cafga_captum/attr/_core/feature_ablation.py
cafga/explainers/cafga_captum/attr/_core/kernel_shap.py
cafga/explainers/cafga_captum/attr/_core/lime.py
cafga/explainers/cafga_captum/attr/_core/shapley_value.py
cafga/explainers/cafga_captum/attr/_models/__init__.py
cafga/explainers/cafga_captum/attr/_models/base.py
cafga/explainers/cafga_captum/attr/_utils/__init__.py
cafga/explainers/cafga_captum/attr/_utils/approximation_methods.py
cafga/explainers/cafga_captum/attr/_utils/attribution.py
cafga/explainers/cafga_captum/attr/_utils/baselines.py
cafga/explainers/cafga_captum/attr/_utils/batching.py
cafga/explainers/cafga_captum/attr/_utils/class_summarizer.py
cafga/explainers/cafga_captum/attr/_utils/common.py
cafga/explainers/cafga_captum/attr/_utils/custom_modules.py
cafga/explainers/cafga_captum/attr/_utils/input_layer_wrapper.py
cafga/explainers/cafga_captum/attr/_utils/interpretable_input.py
cafga/explainers/cafga_captum/attr/_utils/lrp_rules.py
cafga-0.0.6.dist-info/METADATA
cafga-0.0.6.dist-info/WHEEL
cafga-0.0.6.dist-info/top_level.txt
cafga-0.0.6.dist-info/RECORD
