Metadata-Version: 2.4
Name: cafga
Version: 0.0.6
Summary: CafGa is a library that facilitates creating and evaluating grouped-attribution explanations.
Author-email: Alan Boyle <aboyle@student.ethz.ch>
Keywords: LLM,XAI,NLP,salience,attribution
Classifier: Programming Language :: Python :: 3
Classifier: License :: OSI Approved :: BSD License
Requires-Python: >=3.10
Requires-Dist: pip
Requires-Dist: matplotlib>=3.10.0
Requires-Dist: numpy==2.0.0
Requires-Dist: pandas>=2
Requires-Dist: black>=25
Requires-Dist: python-dotenv>=1.0
Requires-Dist: pyyaml>=6.0
Requires-Dist: pydantic>=2.10
Requires-Dist: sacremoses>=0.1.1
Requires-Dist: openai>=1.63.0
Requires-Dist: nltk>=3.8
